{"version":1,"sources":[{"meta":{"id":"20260721-162347-4qwx","dateStart":"2026-07-21T20:23:47.000Z","dateEnd":"2026-07-21T20:59:54.000Z","generatedAt":"2026-07-21T21:12:24.918Z"},"stats":{"statsViewSettings":{"noEgoMode":false},"commanderStats":{"rows":[{"key":"Clapp.8534","account":"Clapp.8534","characterNames":["C L A P P"],"profession":"Dragonhunter","fights":24,"kills":534,"downs":763,"commanderDeaths":0,"alliesDead":226,"wins":21,"losses":3}]},"attendanceData":[{"account":"Alexcion.1359","characterNames":["Sand By Me"],"combatTimeMs":4356999,"squadTimeMs":5527929,"classTimes":[{"profession":"Scourge","timeMs":4356999}]},{"account":"bobcatrufus.3079","characterNames":["Bobcat Rufus"],"combatTimeMs":4398847,"squadTimeMs":5527929,"classTimes":[{"profession":"Luminary","timeMs":4398847}]},{"account":"BravelyRanAway.4625","characterNames":["Knight Takes Castle"],"combatTimeMs":4461132,"squadTimeMs":5527929,"classTimes":[{"profession":"Firebrand","timeMs":4461132}]},{"account":"Clapp.8534","characterNames":["C L A P P"],"combatTimeMs":4576714,"squadTimeMs":5527929,"classTimes":[{"profession":"Dragonhunter","timeMs":4576714}]},{"account":"DarkHeart.1760","characterNames":["Harken Darkheart"],"combatTimeMs":4268734,"squadTimeMs":5527929,"classTimes":[{"profession":"Conduit","timeMs":4268734}]},{"account":"Dirt Nap.7653","characterNames":["Sweating Oldies"],"combatTimeMs":4538594,"squadTimeMs":5527929,"classTimes":[{"profession":"Tempest","timeMs":4538594}]},{"account":"Dovey.8249","characterNames":["Wicked Dovey"],"combatTimeMs":4493957,"squadTimeMs":5527929,"classTimes":[{"profession":"Tempest","timeMs":4493957}]},{"account":"Fay.8071","characterNames":["Ryñnä"],"combatTimeMs":4575093,"squadTimeMs":5527929,"classTimes":[{"profession":"Scrapper","timeMs":4575093}]},{"account":"Ghosttttt.8240","characterNames":["I M A U L I"],"combatTimeMs":4372308,"squadTimeMs":5527929,"classTimes":[{"profession":"Conduit","timeMs":4372308}]},{"account":"inneedoflife.5092","characterNames":["Windows Key Plus L"],"combatTimeMs":4446369,"squadTimeMs":5527929,"classTimes":[{"profession":"Spellbreaker","timeMs":4446369}]},{"account":"Isis.6803","characterNames":["I Like Loud Noises"],"combatTimeMs":4374129,"squadTimeMs":5527929,"classTimes":[{"profession":"Amalgam","timeMs":4374129}]},{"account":"Krisp.9538","characterNames":["Kwithpykweam"],"combatTimeMs":4087637,"squadTimeMs":5527929,"classTimes":[{"profession":"Daredevil","timeMs":4087637}]},{"account":"leiiidees.9684","characterNames":["Akainohime"],"combatTimeMs":4529631,"squadTimeMs":5527929,"classTimes":[{"profession":"Tempest","timeMs":4529631}]},{"account":"Lightbulbstunner.8314","characterNames":["Badlight"],"combatTimeMs":4253202,"squadTimeMs":5527929,"classTimes":[{"profession":"Ranger","timeMs":4253202}]},{"account":"Mangui.3850","characterNames":["Paw Klawzynski"],"combatTimeMs":4462427,"squadTimeMs":5527929,"classTimes":[{"profession":"Scrapper","timeMs":4462427}]},{"account":"Matygon.8406","characterNames":["Matylda Windpiercer"],"combatTimeMs":3734426,"squadTimeMs":5527929,"classTimes":[{"profession":"Untamed","timeMs":3734426}]},{"account":"ocommodos.7103","characterNames":["Oushia"],"combatTimeMs":4365900,"squadTimeMs":5527929,"classTimes":[{"profession":"Dragonhunter","timeMs":4283323},{"profession":"Guardian","timeMs":82577}]},{"account":"Ren.4150","characterNames":["Rayne Ames"],"combatTimeMs":4457301,"squadTimeMs":5527929,"classTimes":[{"profession":"Evoker","timeMs":4457301}]},{"account":"Roku.7865","characterNames":["Devill Dolphinn"],"combatTimeMs":4485847,"squadTimeMs":5527929,"classTimes":[{"profession":"Druid","timeMs":4485847}]},{"account":"Silverblade.3052","characterNames":["Arwenthiel Silveran"],"combatTimeMs":4568704,"squadTimeMs":5527929,"classTimes":[{"profession":"Galeshot","timeMs":4568704}]},{"account":"Taco Cat.9871","characterNames":["Aoife Sliabh"],"combatTimeMs":4569221,"squadTimeMs":5527929,"classTimes":[{"profession":"Druid","timeMs":4569221}]},{"account":"TLukke.8724","characterNames":["Tylukke"],"combatTimeMs":4312258,"squadTimeMs":5527929,"classTimes":[{"profession":"Firebrand","timeMs":4312258}]},{"account":"Vonoska.9812","characterNames":["Honoska"],"combatTimeMs":3325202,"squadTimeMs":5360086,"classTimes":[{"profession":"Troubadour","timeMs":3325202}]},{"account":"Absolut.4867","characterNames":["Aßsolut Citron"],"combatTimeMs":2790709,"squadTimeMs":5183061,"classTimes":[{"profession":"Spellbreaker","timeMs":2790709}]},{"account":"Bran.5384","characterNames":["Bran Knorths"],"combatTimeMs":3799451,"squadTimeMs":5183061,"classTimes":[{"profession":"Paragon","timeMs":3799451}]},{"account":"Eclipse.4138","characterNames":["Elunabell"],"combatTimeMs":3633671,"squadTimeMs":5183061,"classTimes":[{"profession":"Renegade","timeMs":3509215},{"profession":"Vindicator","timeMs":124456}]},{"account":"ELCaptain.3256","characterNames":["Eyes Of Chaos"],"combatTimeMs":4300504,"squadTimeMs":5183061,"classTimes":[{"profession":"Troubadour","timeMs":3720031},{"profession":"Mirage","timeMs":580473}]},{"account":"Durakzel.4681","characterNames":["Durakzel"],"combatTimeMs":4050927,"squadTimeMs":4997929,"classTimes":[{"profession":"Evoker","timeMs":4050927}]},{"account":"Lastflag.3714","characterNames":["Ghostflag"],"combatTimeMs":4054142,"squadTimeMs":4997929,"classTimes":[{"profession":"Untamed","timeMs":4054142}]},{"account":"Omenx.2138","characterNames":["Omenzer"],"combatTimeMs":3974191,"squadTimeMs":4997929,"classTimes":[{"profession":"Necromancer","timeMs":3974191}]},{"account":"Stingray.4153","characterNames":["Rowan Greenrun"],"combatTimeMs":4081381,"squadTimeMs":4997929,"classTimes":[{"profession":"Druid","timeMs":4081381}]},{"account":"Wildrhubarb.8704","characterNames":["Laranel Esseheim"],"combatTimeMs":3941241,"squadTimeMs":4997929,"classTimes":[{"profession":"Amalgam","timeMs":3941241}]},{"account":"Chronotics.5781","characterNames":["Grimgar Azurflame"],"combatTimeMs":3156084,"squadTimeMs":4127929,"classTimes":[{"profession":"Luminary","timeMs":3156084}]},{"account":"vicki.6943","characterNames":["Big Carrot"],"combatTimeMs":3290063,"squadTimeMs":4127929,"classTimes":[{"profession":"Tempest","timeMs":3196859},{"profession":"Elementalist","timeMs":93204}]},{"account":"Elandriel.7934","characterNames":["Qüinçy"],"combatTimeMs":3146214,"squadTimeMs":3932488,"classTimes":[{"profession":"Druid","timeMs":3146214}]},{"account":"Wraithwulf.3614","characterNames":["Wraith Wulfsin"],"combatTimeMs":3206123,"squadTimeMs":3805564,"classTimes":[{"profession":"Spellbreaker","timeMs":3206123}]},{"account":"Pandorum.2834","characterNames":["P Ó R R"],"combatTimeMs":2126191,"squadTimeMs":3215929,"classTimes":[{"profession":"Dragonhunter","timeMs":2126191}]},{"account":"Captain Devo.8790","characterNames":["Dawn Of Erollisi"],"combatTimeMs":1692622,"squadTimeMs":2985760,"classTimes":[{"profession":"Guardian","timeMs":1692622}]},{"account":"Sukata.2863","characterNames":["Sukata Lhone"],"combatTimeMs":1819932,"squadTimeMs":2871061,"classTimes":[{"profession":"Druid","timeMs":1819932}]},{"account":"LittleEcho.2510","characterNames":["Lileko"],"combatTimeMs":2395297,"squadTimeMs":2770226,"classTimes":[{"profession":"Evoker","timeMs":2395297}]},{"account":"Zaul.6198","characterNames":["Stoic Illusion"],"combatTimeMs":2475643,"squadTimeMs":2770226,"classTimes":[{"profession":"Virtuoso","timeMs":2475643}]},{"account":"Brave Mallyki.1563","characterNames":["Dark Lord Mallyki"],"combatTimeMs":2326639,"squadTimeMs":2726801,"classTimes":[{"profession":"Reaper","timeMs":1938819},{"profession":"Harbinger","timeMs":387820}]},{"account":"Pixel Precision.8572","characterNames":["Riker Deadshot"],"combatTimeMs":2419819,"squadTimeMs":2726801,"classTimes":[{"profession":"Mechanist","timeMs":2419819}]},{"account":"Tig.3685","characterNames":["Tyggii"],"combatTimeMs":2416016,"squadTimeMs":2726801,"classTimes":[{"profession":"Scourge","timeMs":2409253},{"profession":"Necromancer","timeMs":6763}]},{"account":"Validity.2013","characterNames":["Validitea"],"combatTimeMs":2430911,"squadTimeMs":2726801,"classTimes":[{"profession":"Luminary","timeMs":2430911}]},{"account":"DatBruceWayne.2357","characterNames":["Liquid Snakë I"],"combatTimeMs":1968015,"squadTimeMs":2677929,"classTimes":[{"profession":"Reaper","timeMs":1968015}]},{"account":"totanyffy.3846","characterNames":["Taffy Candy"],"combatTimeMs":2006958,"squadTimeMs":2677929,"classTimes":[{"profession":"Virtuoso","timeMs":2006958}]},{"account":"DeeKay.2401","characterNames":["Ancient Eclipse"],"combatTimeMs":1616225,"squadTimeMs":2607863,"classTimes":[{"profession":"Reaper","timeMs":1616225}]},{"account":"Meajji.2650","characterNames":["Shaman Hhuinn"],"combatTimeMs":1937713,"squadTimeMs":2410929,"classTimes":[{"profession":"Ritualist","timeMs":1937713}]},{"account":"trop.2463","characterNames":["Trop Gremista"],"combatTimeMs":1560818,"squadTimeMs":2410929,"classTimes":[{"profession":"Reaper","timeMs":1560818}]},{"account":"beefycvkes.8045","characterNames":["T R V S H"],"combatTimeMs":1943631,"squadTimeMs":2254557,"classTimes":[{"profession":"Luminary","timeMs":1943631}]},{"account":"Duill.4625","characterNames":["Lylla Duill"],"combatTimeMs":1903884,"squadTimeMs":2254557,"classTimes":[{"profession":"Luminary","timeMs":1903884}]},{"account":"Ian.6847","characterNames":["Signy Steeldottir"],"combatTimeMs":1742893,"squadTimeMs":2254557,"classTimes":[{"profession":"Dragonhunter","timeMs":1742893}]},{"account":"Mashed Potatoes.7264","characterNames":["Shayla Quickshot"],"combatTimeMs":1741245,"squadTimeMs":2254557,"classTimes":[{"profession":"Galeshot","timeMs":1741245}]},{"account":"philong.3745","characterNames":["Philong Nguyenx"],"combatTimeMs":1921043,"squadTimeMs":2254557,"classTimes":[{"profession":"Reaper","timeMs":1921043}]},{"account":"Tufis.5147","characterNames":["Tufis Macake"],"combatTimeMs":1623363,"squadTimeMs":2166929,"classTimes":[{"profession":"Evoker","timeMs":1623363}]},{"account":"Cahli.7985","characterNames":["Cahli Ele"],"combatTimeMs":1442924,"squadTimeMs":1847602,"classTimes":[{"profession":"Tempest","timeMs":1442924}]},{"account":"Bertrand Sablefort.9182","characterNames":["Bertrand Sablefort"],"combatTimeMs":1237814,"squadTimeMs":1686929,"classTimes":[{"profession":"Scourge","timeMs":1237814}]},{"account":"SignifiedSatyr.2351","characterNames":["Champión Keep Lórd"],"combatTimeMs":1042664,"squadTimeMs":1357929,"classTimes":[{"profession":"Luminary","timeMs":1042664}]},{"account":"demoncat.2983","characterNames":["Farne Shadowclaw"],"combatTimeMs":1098502,"squadTimeMs":1323354,"classTimes":[{"profession":"Amalgam","timeMs":1098502}]},{"account":"Nelah Nav Eidde.4753","characterNames":["Kill Dagger"],"combatTimeMs":1113969,"squadTimeMs":1323354,"classTimes":[{"profession":"Scourge","timeMs":1113969}]},{"account":"Snowyi.9630","characterNames":["Snap Cracle And Pop"],"combatTimeMs":816664,"squadTimeMs":1323354,"classTimes":[{"profession":"Troubadour","timeMs":816664}]},{"account":"Vorden.2349","characterNames":["Just A Hedge"],"combatTimeMs":594593,"squadTimeMs":1323354,"classTimes":[{"profession":"Daredevil","timeMs":594593}]},{"account":"Milot.8165","characterNames":["Mossdancer Milot"],"combatTimeMs":386250,"squadTimeMs":1138061,"classTimes":[{"profession":"Virtuoso","timeMs":386250}]},{"account":"Serilkath.7365","characterNames":["Taliesin Serilkath"],"combatTimeMs":814880,"squadTimeMs":1035929,"classTimes":[{"profession":"Specter","timeMs":814880}]},{"account":"Sterissa.4782","characterNames":["Elementalissa"],"combatTimeMs":322176,"squadTimeMs":868086,"classTimes":[{"profession":"Weaver","timeMs":322176}]},{"account":"Blackimbo.9543","characterNames":["Blackkimbo"],"combatTimeMs":557448,"squadTimeMs":688564,"classTimes":[{"profession":"Revenant","timeMs":557448}]},{"account":"Alydia.7612","characterNames":["Alydia Shadowmere"],"combatTimeMs":372118,"squadTimeMs":434145,"classTimes":[{"profession":"Reaper","timeMs":372118}]},{"account":"Colorian.5067","characterNames":["Colorian Matic"],"combatTimeMs":282999,"squadTimeMs":321606,"classTimes":[{"profession":"Berserker","timeMs":282999}]},{"account":"Skippy.9671","characterNames":["Skippy Sagekeeper"],"combatTimeMs":198853,"squadTimeMs":287929,"classTimes":[{"profession":"Druid","timeMs":198853}]},{"account":"Spicy Coke.1928","characterNames":["Goo Dan"],"combatTimeMs":181835,"squadTimeMs":287929,"classTimes":[{"profession":"Scourge","timeMs":181835}]}]}}],"rollup":{"commanderRows":[{"account":"Clapp.8534","characterNames":["C L A P P"],"profession":"Dragonhunter","professionBreakdown":[{"profession":"Dragonhunter","runs":1}],"runs":1,"fightsLed":24,"kills":534,"downs":763,"commanderDeaths":0,"alliesDead":226,"wins":21,"losses":3,"kdr":2.3628318584070795,"lastSeenTs":1784667594000}],"playerRows":[{"account":"Alexcion.1359","characterNames":["Sand By Me"],"profession":"Scourge","professionBreakdown":[{"profession":"Scourge","runs":1}],"runs":1,"combatTimeMs":4356999,"squadTimeMs":5527929,"lastSeenTs":1784667594000},{"account":"bobcatrufus.3079","characterNames":["Bobcat Rufus"],"profession":"Luminary","professionBreakdown":[{"profession":"Luminary","runs":1}],"runs":1,"combatTimeMs":4398847,"squadTimeMs":5527929,"lastSeenTs":1784667594000},{"account":"BravelyRanAway.4625","characterNames":["Knight Takes Castle"],"profession":"Firebrand","professionBreakdown":[{"profession":"Firebrand","runs":1}],"runs":1,"combatTimeMs":4461132,"squadTimeMs":5527929,"lastSeenTs":1784667594000},{"account":"Clapp.8534","characterNames":["C L A P P"],"profession":"Dragonhunter","professionBreakdown":[{"profession":"Dragonhunter","runs":1}],"runs":1,"combatTimeMs":4576714,"squadTimeMs":5527929,"lastSeenTs":1784667594000},{"account":"DarkHeart.1760","characterNames":["Harken Darkheart"],"profession":"Conduit","professionBreakdown":[{"profession":"Conduit","runs":1}],"runs":1,"combatTimeMs":4268734,"squadTimeMs":5527929,"lastSeenTs":1784667594000},{"account":"Dirt Nap.7653","characterNames":["Sweating Oldies"],"profession":"Tempest","professionBreakdown":[{"profession":"Tempest","runs":1}],"runs":1,"combatTimeMs":4538594,"squadTimeMs":5527929,"lastSeenTs":1784667594000},{"account":"Dovey.8249","characterNames":["Wicked Dovey"],"profession":"Tempest","professionBreakdown":[{"profession":"Tempest","runs":1}],"runs":1,"combatTimeMs":4493957,"squadTimeMs":5527929,"lastSeenTs":1784667594000},{"account":"Fay.8071","characterNames":["Ryñnä"],"profession":"Scrapper","professionBreakdown":[{"profession":"Scrapper","runs":1}],"runs":1,"combatTimeMs":4575093,"squadTimeMs":5527929,"lastSeenTs":1784667594000},{"account":"Ghosttttt.8240","characterNames":["I M A U L I"],"profession":"Conduit","professionBreakdown":[{"profession":"Conduit","runs":1}],"runs":1,"combatTimeMs":4372308,"squadTimeMs":5527929,"lastSeenTs":1784667594000},{"account":"inneedoflife.5092","characterNames":["Windows Key Plus L"],"profession":"Spellbreaker","professionBreakdown":[{"profession":"Spellbreaker","runs":1}],"runs":1,"combatTimeMs":4446369,"squadTimeMs":5527929,"lastSeenTs":1784667594000},{"account":"Isis.6803","characterNames":["I Like Loud Noises"],"profession":"Amalgam","professionBreakdown":[{"profession":"Amalgam","runs":1}],"runs":1,"combatTimeMs":4374129,"squadTimeMs":5527929,"lastSeenTs":1784667594000},{"account":"Krisp.9538","characterNames":["Kwithpykweam"],"profession":"Daredevil","professionBreakdown":[{"profession":"Daredevil","runs":1}],"runs":1,"combatTimeMs":4087637,"squadTimeMs":5527929,"lastSeenTs":1784667594000},{"account":"leiiidees.9684","characterNames":["Akainohime"],"profession":"Tempest","professionBreakdown":[{"profession":"Tempest","runs":1}],"runs":1,"combatTimeMs":4529631,"squadTimeMs":5527929,"lastSeenTs":1784667594000},{"account":"Lightbulbstunner.8314","characterNames":["Badlight"],"profession":"Ranger","professionBreakdown":[{"profession":"Ranger","runs":1}],"runs":1,"combatTimeMs":4253202,"squadTimeMs":5527929,"lastSeenTs":1784667594000},{"account":"Mangui.3850","characterNames":["Paw Klawzynski"],"profession":"Scrapper","professionBreakdown":[{"profession":"Scrapper","runs":1}],"runs":1,"combatTimeMs":4462427,"squadTimeMs":5527929,"lastSeenTs":1784667594000},{"account":"Matygon.8406","characterNames":["Matylda Windpiercer"],"profession":"Untamed","professionBreakdown":[{"profession":"Untamed","runs":1}],"runs":1,"combatTimeMs":3734426,"squadTimeMs":5527929,"lastSeenTs":1784667594000},{"account":"ocommodos.7103","characterNames":["Oushia"],"profession":"Dragonhunter","professionBreakdown":[{"profession":"Dragonhunter","runs":1},{"profession":"Guardian","runs":1}],"runs":1,"combatTimeMs":4365900,"squadTimeMs":5527929,"lastSeenTs":1784667594000},{"account":"Ren.4150","characterNames":["Rayne Ames"],"profession":"Evoker","professionBreakdown":[{"profession":"Evoker","runs":1}],"runs":1,"combatTimeMs":4457301,"squadTimeMs":5527929,"lastSeenTs":1784667594000},{"account":"Roku.7865","characterNames":["Devill Dolphinn"],"profession":"Druid","professionBreakdown":[{"profession":"Druid","runs":1}],"runs":1,"combatTimeMs":4485847,"squadTimeMs":5527929,"lastSeenTs":1784667594000},{"account":"Silverblade.3052","characterNames":["Arwenthiel Silveran"],"profession":"Galeshot","professionBreakdown":[{"profession":"Galeshot","runs":1}],"runs":1,"combatTimeMs":4568704,"squadTimeMs":5527929,"lastSeenTs":1784667594000},{"account":"Taco Cat.9871","characterNames":["Aoife Sliabh"],"profession":"Druid","professionBreakdown":[{"profession":"Druid","runs":1}],"runs":1,"combatTimeMs":4569221,"squadTimeMs":5527929,"lastSeenTs":1784667594000},{"account":"TLukke.8724","characterNames":["Tylukke"],"profession":"Firebrand","professionBreakdown":[{"profession":"Firebrand","runs":1}],"runs":1,"combatTimeMs":4312258,"squadTimeMs":5527929,"lastSeenTs":1784667594000},{"account":"Vonoska.9812","characterNames":["Honoska"],"profession":"Troubadour","professionBreakdown":[{"profession":"Troubadour","runs":1}],"runs":1,"combatTimeMs":3325202,"squadTimeMs":5360086,"lastSeenTs":1784667594000},{"account":"Absolut.4867","characterNames":["Aßsolut Citron"],"profession":"Spellbreaker","professionBreakdown":[{"profession":"Spellbreaker","runs":1}],"runs":1,"combatTimeMs":2790709,"squadTimeMs":5183061,"lastSeenTs":1784667594000},{"account":"Bran.5384","characterNames":["Bran Knorths"],"profession":"Paragon","professionBreakdown":[{"profession":"Paragon","runs":1}],"runs":1,"combatTimeMs":3799451,"squadTimeMs":5183061,"lastSeenTs":1784667594000},{"account":"Eclipse.4138","characterNames":["Elunabell"],"profession":"Renegade","professionBreakdown":[{"profession":"Renegade","runs":1},{"profession":"Vindicator","runs":1}],"runs":1,"combatTimeMs":3633671,"squadTimeMs":5183061,"lastSeenTs":1784667594000},{"account":"ELCaptain.3256","characterNames":["Eyes Of Chaos"],"profession":"Troubadour","professionBreakdown":[{"profession":"Mirage","runs":1},{"profession":"Troubadour","runs":1}],"runs":1,"combatTimeMs":4300504,"squadTimeMs":5183061,"lastSeenTs":1784667594000},{"account":"Durakzel.4681","characterNames":["Durakzel"],"profession":"Evoker","professionBreakdown":[{"profession":"Evoker","runs":1}],"runs":1,"combatTimeMs":4050927,"squadTimeMs":4997929,"lastSeenTs":1784667594000},{"account":"Lastflag.3714","characterNames":["Ghostflag"],"profession":"Untamed","professionBreakdown":[{"profession":"Untamed","runs":1}],"runs":1,"combatTimeMs":4054142,"squadTimeMs":4997929,"lastSeenTs":1784667594000},{"account":"Omenx.2138","characterNames":["Omenzer"],"profession":"Necromancer","professionBreakdown":[{"profession":"Necromancer","runs":1}],"runs":1,"combatTimeMs":3974191,"squadTimeMs":4997929,"lastSeenTs":1784667594000},{"account":"Stingray.4153","characterNames":["Rowan Greenrun"],"profession":"Druid","professionBreakdown":[{"profession":"Druid","runs":1}],"runs":1,"combatTimeMs":4081381,"squadTimeMs":4997929,"lastSeenTs":1784667594000},{"account":"Wildrhubarb.8704","characterNames":["Laranel Esseheim"],"profession":"Amalgam","professionBreakdown":[{"profession":"Amalgam","runs":1}],"runs":1,"combatTimeMs":3941241,"squadTimeMs":4997929,"lastSeenTs":1784667594000},{"account":"Chronotics.5781","characterNames":["Grimgar Azurflame"],"profession":"Luminary","professionBreakdown":[{"profession":"Luminary","runs":1}],"runs":1,"combatTimeMs":3156084,"squadTimeMs":4127929,"lastSeenTs":1784667594000},{"account":"vicki.6943","characterNames":["Big Carrot"],"profession":"Tempest","professionBreakdown":[{"profession":"Elementalist","runs":1},{"profession":"Tempest","runs":1}],"runs":1,"combatTimeMs":3290063,"squadTimeMs":4127929,"lastSeenTs":1784667594000},{"account":"Elandriel.7934","characterNames":["Qüinçy"],"profession":"Druid","professionBreakdown":[{"profession":"Druid","runs":1}],"runs":1,"combatTimeMs":3146214,"squadTimeMs":3932488,"lastSeenTs":1784667594000},{"account":"Wraithwulf.3614","characterNames":["Wraith Wulfsin"],"profession":"Spellbreaker","professionBreakdown":[{"profession":"Spellbreaker","runs":1}],"runs":1,"combatTimeMs":3206123,"squadTimeMs":3805564,"lastSeenTs":1784667594000},{"account":"Pandorum.2834","characterNames":["P Ó R R"],"profession":"Dragonhunter","professionBreakdown":[{"profession":"Dragonhunter","runs":1}],"runs":1,"combatTimeMs":2126191,"squadTimeMs":3215929,"lastSeenTs":1784667594000},{"account":"Captain Devo.8790","characterNames":["Dawn Of Erollisi"],"profession":"Guardian","professionBreakdown":[{"profession":"Guardian","runs":1}],"runs":1,"combatTimeMs":1692622,"squadTimeMs":2985760,"lastSeenTs":1784667594000},{"account":"Sukata.2863","characterNames":["Sukata Lhone"],"profession":"Druid","professionBreakdown":[{"profession":"Druid","runs":1}],"runs":1,"combatTimeMs":1819932,"squadTimeMs":2871061,"lastSeenTs":1784667594000},{"account":"LittleEcho.2510","characterNames":["Lileko"],"profession":"Evoker","professionBreakdown":[{"profession":"Evoker","runs":1}],"runs":1,"combatTimeMs":2395297,"squadTimeMs":2770226,"lastSeenTs":1784667594000},{"account":"Zaul.6198","characterNames":["Stoic Illusion"],"profession":"Virtuoso","professionBreakdown":[{"profession":"Virtuoso","runs":1}],"runs":1,"combatTimeMs":2475643,"squadTimeMs":2770226,"lastSeenTs":1784667594000},{"account":"Brave Mallyki.1563","characterNames":["Dark Lord Mallyki"],"profession":"Reaper","professionBreakdown":[{"profession":"Harbinger","runs":1},{"profession":"Reaper","runs":1}],"runs":1,"combatTimeMs":2326639,"squadTimeMs":2726801,"lastSeenTs":1784667594000},{"account":"Pixel Precision.8572","characterNames":["Riker Deadshot"],"profession":"Mechanist","professionBreakdown":[{"profession":"Mechanist","runs":1}],"runs":1,"combatTimeMs":2419819,"squadTimeMs":2726801,"lastSeenTs":1784667594000},{"account":"Tig.3685","characterNames":["Tyggii"],"profession":"Scourge","professionBreakdown":[{"profession":"Necromancer","runs":1},{"profession":"Scourge","runs":1}],"runs":1,"combatTimeMs":2416016,"squadTimeMs":2726801,"lastSeenTs":1784667594000},{"account":"Validity.2013","characterNames":["Validitea"],"profession":"Luminary","professionBreakdown":[{"profession":"Luminary","runs":1}],"runs":1,"combatTimeMs":2430911,"squadTimeMs":2726801,"lastSeenTs":1784667594000},{"account":"DatBruceWayne.2357","characterNames":["Liquid Snakë I"],"profession":"Reaper","professionBreakdown":[{"profession":"Reaper","runs":1}],"runs":1,"combatTimeMs":1968015,"squadTimeMs":2677929,"lastSeenTs":1784667594000},{"account":"totanyffy.3846","characterNames":["Taffy Candy"],"profession":"Virtuoso","professionBreakdown":[{"profession":"Virtuoso","runs":1}],"runs":1,"combatTimeMs":2006958,"squadTimeMs":2677929,"lastSeenTs":1784667594000},{"account":"DeeKay.2401","characterNames":["Ancient Eclipse"],"profession":"Reaper","professionBreakdown":[{"profession":"Reaper","runs":1}],"runs":1,"combatTimeMs":1616225,"squadTimeMs":2607863,"lastSeenTs":1784667594000},{"account":"Meajji.2650","characterNames":["Shaman Hhuinn"],"profession":"Ritualist","professionBreakdown":[{"profession":"Ritualist","runs":1}],"runs":1,"combatTimeMs":1937713,"squadTimeMs":2410929,"lastSeenTs":1784667594000},{"account":"trop.2463","characterNames":["Trop Gremista"],"profession":"Reaper","professionBreakdown":[{"profession":"Reaper","runs":1}],"runs":1,"combatTimeMs":1560818,"squadTimeMs":2410929,"lastSeenTs":1784667594000},{"account":"beefycvkes.8045","characterNames":["T R V S H"],"profession":"Luminary","professionBreakdown":[{"profession":"Luminary","runs":1}],"runs":1,"combatTimeMs":1943631,"squadTimeMs":2254557,"lastSeenTs":1784667594000},{"account":"Duill.4625","characterNames":["Lylla Duill"],"profession":"Luminary","professionBreakdown":[{"profession":"Luminary","runs":1}],"runs":1,"combatTimeMs":1903884,"squadTimeMs":2254557,"lastSeenTs":1784667594000},{"account":"Ian.6847","characterNames":["Signy Steeldottir"],"profession":"Dragonhunter","professionBreakdown":[{"profession":"Dragonhunter","runs":1}],"runs":1,"combatTimeMs":1742893,"squadTimeMs":2254557,"lastSeenTs":1784667594000},{"account":"Mashed Potatoes.7264","characterNames":["Shayla Quickshot"],"profession":"Galeshot","professionBreakdown":[{"profession":"Galeshot","runs":1}],"runs":1,"combatTimeMs":1741245,"squadTimeMs":2254557,"lastSeenTs":1784667594000},{"account":"philong.3745","characterNames":["Philong Nguyenx"],"profession":"Reaper","professionBreakdown":[{"profession":"Reaper","runs":1}],"runs":1,"combatTimeMs":1921043,"squadTimeMs":2254557,"lastSeenTs":1784667594000},{"account":"Tufis.5147","characterNames":["Tufis Macake"],"profession":"Evoker","professionBreakdown":[{"profession":"Evoker","runs":1}],"runs":1,"combatTimeMs":1623363,"squadTimeMs":2166929,"lastSeenTs":1784667594000},{"account":"Cahli.7985","characterNames":["Cahli Ele"],"profession":"Tempest","professionBreakdown":[{"profession":"Tempest","runs":1}],"runs":1,"combatTimeMs":1442924,"squadTimeMs":1847602,"lastSeenTs":1784667594000},{"account":"Bertrand Sablefort.9182","characterNames":["Bertrand Sablefort"],"profession":"Scourge","professionBreakdown":[{"profession":"Scourge","runs":1}],"runs":1,"combatTimeMs":1237814,"squadTimeMs":1686929,"lastSeenTs":1784667594000},{"account":"SignifiedSatyr.2351","characterNames":["Champión Keep Lórd"],"profession":"Luminary","professionBreakdown":[{"profession":"Luminary","runs":1}],"runs":1,"combatTimeMs":1042664,"squadTimeMs":1357929,"lastSeenTs":1784667594000},{"account":"demoncat.2983","characterNames":["Farne Shadowclaw"],"profession":"Amalgam","professionBreakdown":[{"profession":"Amalgam","runs":1}],"runs":1,"combatTimeMs":1098502,"squadTimeMs":1323354,"lastSeenTs":1784667594000},{"account":"Nelah Nav Eidde.4753","characterNames":["Kill Dagger"],"profession":"Scourge","professionBreakdown":[{"profession":"Scourge","runs":1}],"runs":1,"combatTimeMs":1113969,"squadTimeMs":1323354,"lastSeenTs":1784667594000},{"account":"Snowyi.9630","characterNames":["Snap Cracle And Pop"],"profession":"Troubadour","professionBreakdown":[{"profession":"Troubadour","runs":1}],"runs":1,"combatTimeMs":816664,"squadTimeMs":1323354,"lastSeenTs":1784667594000},{"account":"Vorden.2349","characterNames":["Just A Hedge"],"profession":"Daredevil","professionBreakdown":[{"profession":"Daredevil","runs":1}],"runs":1,"combatTimeMs":594593,"squadTimeMs":1323354,"lastSeenTs":1784667594000},{"account":"Milot.8165","characterNames":["Mossdancer Milot"],"profession":"Virtuoso","professionBreakdown":[{"profession":"Virtuoso","runs":1}],"runs":1,"combatTimeMs":386250,"squadTimeMs":1138061,"lastSeenTs":1784667594000},{"account":"Serilkath.7365","characterNames":["Taliesin Serilkath"],"profession":"Specter","professionBreakdown":[{"profession":"Specter","runs":1}],"runs":1,"combatTimeMs":814880,"squadTimeMs":1035929,"lastSeenTs":1784667594000},{"account":"Sterissa.4782","characterNames":["Elementalissa"],"profession":"Weaver","professionBreakdown":[{"profession":"Weaver","runs":1}],"runs":1,"combatTimeMs":322176,"squadTimeMs":868086,"lastSeenTs":1784667594000},{"account":"Blackimbo.9543","characterNames":["Blackkimbo"],"profession":"Revenant","professionBreakdown":[{"profession":"Revenant","runs":1}],"runs":1,"combatTimeMs":557448,"squadTimeMs":688564,"lastSeenTs":1784667594000},{"account":"Alydia.7612","characterNames":["Alydia Shadowmere"],"profession":"Reaper","professionBreakdown":[{"profession":"Reaper","runs":1}],"runs":1,"combatTimeMs":372118,"squadTimeMs":434145,"lastSeenTs":1784667594000},{"account":"Colorian.5067","characterNames":["Colorian Matic"],"profession":"Berserker","professionBreakdown":[{"profession":"Berserker","runs":1}],"runs":1,"combatTimeMs":282999,"squadTimeMs":321606,"lastSeenTs":1784667594000},{"account":"Skippy.9671","characterNames":["Skippy Sagekeeper"],"profession":"Druid","professionBreakdown":[{"profession":"Druid","runs":1}],"runs":1,"combatTimeMs":198853,"squadTimeMs":287929,"lastSeenTs":1784667594000},{"account":"Spicy Coke.1928","characterNames":["Goo Dan"],"profession":"Scourge","professionBreakdown":[{"profession":"Scourge","runs":1}],"runs":1,"combatTimeMs":181835,"squadTimeMs":287929,"lastSeenTs":1784667594000}],"sourceReports":1,"uniqueRaids":1,"duplicateReportsCollapsed":0,"raidsSkippedMissingRequiredData":0,"reportsWithCommanderDetails":1,"reportsMissingCommanderDetails":0,"reportsWithAttendanceDetails":1,"reportsMissingAttendanceDetails":0,"noEgoMode":false}}